files/__init__.py
files/__main__.py
files/stopwatch.py
files/stopwatch_custom_time.py
files/stopwatch_default.py
files/ting-tong.mp3
Pomodoro_AHP-0.9.1.dist-info/LICENSE.txt
Pomodoro_AHP-0.9.1.dist-info/METADATA
Pomodoro_AHP-0.9.1.dist-info/WHEEL
Pomodoro_AHP-0.9.1.dist-info/entry_points.txt
Pomodoro_AHP-0.9.1.dist-info/top_level.txt
Pomodoro_AHP-0.9.1.dist-info/RECORD
