Metadata-Version: 2.1
Name: Pomodoro_AHP
Version: 0.9.1
Summary: CLI implementation of "Pomodoro Timer" written in Python
Home-page: https://github.com/you-know-wh0/Pomodoro-Timer-2
Author: Prova, Rashid
Author-email: zamiulrashid1@gmail.com, azrahumayraprova@gmail.com
License: MIT
Classifier: License :: OSI Approved :: MIT License
Classifier: Programming Language :: Python :: 3.10
Classifier: Operating System :: OS Independent
Requires-Python: >=3.10
License-File: LICENSE.txt
Requires-Dist: pygame
Requires-Dist: keyboard
